{"nodes": [{"id": "users_abdullah_waslaq_app_lib_core_storage_isar_product_cache_dart", "label": "product_cache.dart", "file_type": "code", "source_file": "lib/core/storage/isar/product_cache.dart", "source_location": null}, {"id": "isar_product_cache_productcache", "label": "ProductCache", "file_type": "code", "source_file": "lib/core/storage/isar/product_cache.dart", "source_location": null}, {"id": "annotation_collection", "label": "@collection", "file_type": "concept", "source_file": null, "source_location": null}, {"id": "isar_product_cache_id", "label": "id", "file_type": "code", "source_file": "lib/core/storage/isar/product_cache.dart", "source_location": null}, {"id": "id", "label": "Id", "file_type": "code", "source_file": null, "source_location": null}, {"id": "isar_product_cache_productid", "label": "productId", "file_type": "code", "source_file": "lib/core/storage/isar/product_cache.dart", "source_location": null}, {"id": "isar_product_cache_title", "label": "title", "file_type": "code", "source_file": "lib/core/storage/isar/product_cache.dart", "source_location": null}, {"id": "isar_product_cache_thumbnail", "label": "thumbnail", "file_type": "code", "source_file": "lib/core/storage/isar/product_cache.dart", "source_location": null}, {"id": "string", "label": "String?", "file_type": "code", "source_file": null, "source_location": null}, {"id": "isar_product_cache_price", "label": "price", "file_type": "code", "source_file": "lib/core/storage/isar/product_cache.dart", "source_location": null}, {"id": "isar_product_cache_vendorname", "label": "vendorName", "file_type": "code", "source_file": "lib/core/storage/isar/product_cache.dart", "source_location": null}, {"id": "isar_product_cache_vendorslug", "label": "vendorSlug", "file_type": "code", "source_file": "lib/core/storage/isar/product_cache.dart", "source_location": null}, {"id": "isar_product_cache_categoryid", "label": "categoryId", "file_type": "code", "source_file": "lib/core/storage/isar/product_cache.dart", "source_location": null}, {"id": "isar_product_cache_cachedjson", "label": "cachedJson", "file_type": "code", "source_file": "lib/core/storage/isar/product_cache.dart", "source_location": null}, {"id": "isar_product_cache_cachedat", "label": "cachedAt", "file_type": "code", "source_file": "lib/core/storage/isar/product_cache.dart", "source_location": null}, {"id": "datetime", "label": "DateTime", "file_type": "code", "source_file": null, "source_location": null}, {"id": "isar_product_cache_isstale", "label": "isStale", "file_type": "code", "source_file": "lib/core/storage/isar/product_cache.dart", "source_location": null}, {"id": "bool_get", "label": "bool get", "file_type": "code", "source_file": null, "source_location": null}, {"id": "package_isar_isar_dart", "label": "package:isar/isar.dart", "file_type": "code", "source_file": null, "source_location": null}], "edges": [{"source": "users_abdullah_waslaq_app_lib_core_storage_isar_product_cache_dart", "target": "isar_product_cache_productcache", "relation": "defines", "confidence": "EXTRACTED", "confidence_score": 1.0, "source_file": "lib/core/storage/isar/product_cache.dart", "source_location": null, "weight": 1.0}, {"source": "isar_product_cache_productcache", "target": "annotation_collection", "relation": "configures", "confidence": "EXTRACTED", "confidence_score": 1.0, "source_file": "lib/core/storage/isar/product_cache.dart", "source_location": null, "weight": 1.0}, {"source": "users_abdullah_waslaq_app_lib_core_storage_isar_product_cache_dart", "target": "isar_product_cache_id", "relation": "defines", "confidence": "EXTRACTED", "confidence_score": 1.0, "source_file": "lib/core/storage/isar/product_cache.dart", "source_location": null, "weight": 1.0}, {"source": "users_abdullah_waslaq_app_lib_core_storage_isar_product_cache_dart", "target": "id", "relation": "references", "confidence": "EXTRACTED", "confidence_score": 1.0, "source_file": "lib/core/storage/isar/product_cache.dart", "source_location": null, "weight": 1.0, "context": "variable_type"}, {"source": "users_abdullah_waslaq_app_lib_core_storage_isar_product_cache_dart", "target": "isar_product_cache_productid", "relation": "defines", "confidence": "EXTRACTED", "confidence_score": 1.0, "source_file": "lib/core/storage/isar/product_cache.dart", "source_location": null, "weight": 1.0}, {"source": "users_abdullah_waslaq_app_lib_core_storage_isar_product_cache_dart", "target": "isar_product_cache_title", "relation": "defines", "confidence": "EXTRACTED", "confidence_score": 1.0, "source_file": "lib/core/storage/isar/product_cache.dart", "source_location": null, "weight": 1.0}, {"source": "users_abdullah_waslaq_app_lib_core_storage_isar_product_cache_dart", "target": "isar_product_cache_thumbnail", "relation": "defines", "confidence": "EXTRACTED", "confidence_score": 1.0, "source_file": "lib/core/storage/isar/product_cache.dart", "source_location": null, "weight": 1.0}, {"source": "users_abdullah_waslaq_app_lib_core_storage_isar_product_cache_dart", "target": "string", "relation": "references", "confidence": "EXTRACTED", "confidence_score": 1.0, "source_file": "lib/core/storage/isar/product_cache.dart", "source_location": null, "weight": 1.0, "context": "variable_type"}, {"source": "users_abdullah_waslaq_app_lib_core_storage_isar_product_cache_dart", "target": "isar_product_cache_price", "relation": "defines", "confidence": "EXTRACTED", "confidence_score": 1.0, "source_file": "lib/core/storage/isar/product_cache.dart", "source_location": null, "weight": 1.0}, {"source": "users_abdullah_waslaq_app_lib_core_storage_isar_product_cache_dart", "target": "isar_product_cache_vendorname", "relation": "defines", "confidence": "EXTRACTED", "confidence_score": 1.0, "source_file": "lib/core/storage/isar/product_cache.dart", "source_location": null, "weight": 1.0}, {"source": "users_abdullah_waslaq_app_lib_core_storage_isar_product_cache_dart", "target": "string", "relation": "references", "confidence": "EXTRACTED", "confidence_score": 1.0, "source_file": "lib/core/storage/isar/product_cache.dart", "source_location": null, "weight": 1.0, "context": "variable_type"}, {"source": "users_abdullah_waslaq_app_lib_core_storage_isar_product_cache_dart", "target": "isar_product_cache_vendorslug", "relation": "defines", "confidence": "EXTRACTED", "confidence_score": 1.0, "source_file": "lib/core/storage/isar/product_cache.dart", "source_location": null, "weight": 1.0}, {"source": "users_abdullah_waslaq_app_lib_core_storage_isar_product_cache_dart", "target": "string", "relation": "references", "confidence": "EXTRACTED", "confidence_score": 1.0, "source_file": "lib/core/storage/isar/product_cache.dart", "source_location": null, "weight": 1.0, "context": "variable_type"}, {"source": "users_abdullah_waslaq_app_lib_core_storage_isar_product_cache_dart", "target": "isar_product_cache_categoryid", "relation": "defines", "confidence": "EXTRACTED", "confidence_score": 1.0, "source_file": "lib/core/storage/isar/product_cache.dart", "source_location": null, "weight": 1.0}, {"source": "users_abdullah_waslaq_app_lib_core_storage_isar_product_cache_dart", "target": "string", "relation": "references", "confidence": "EXTRACTED", "confidence_score": 1.0, "source_file": "lib/core/storage/isar/product_cache.dart", "source_location": null, "weight": 1.0, "context": "variable_type"}, {"source": "users_abdullah_waslaq_app_lib_core_storage_isar_product_cache_dart", "target": "isar_product_cache_cachedjson", "relation": "defines", "confidence": "EXTRACTED", "confidence_score": 1.0, "source_file": "lib/core/storage/isar/product_cache.dart", "source_location": null, "weight": 1.0}, {"source": "users_abdullah_waslaq_app_lib_core_storage_isar_product_cache_dart", "target": "isar_product_cache_cachedat", "relation": "defines", "confidence": "EXTRACTED", "confidence_score": 1.0, "source_file": "lib/core/storage/isar/product_cache.dart", "source_location": null, "weight": 1.0}, {"source": "users_abdullah_waslaq_app_lib_core_storage_isar_product_cache_dart", "target": "datetime", "relation": "references", "confidence": "EXTRACTED", "confidence_score": 1.0, "source_file": "lib/core/storage/isar/product_cache.dart", "source_location": null, "weight": 1.0, "context": "variable_type"}, {"source": "users_abdullah_waslaq_app_lib_core_storage_isar_product_cache_dart", "target": "isar_product_cache_isstale", "relation": "defines", "confidence": "EXTRACTED", "confidence_score": 1.0, "source_file": "lib/core/storage/isar/product_cache.dart", "source_location": null, "weight": 1.0}, {"source": "users_abdullah_waslaq_app_lib_core_storage_isar_product_cache_dart", "target": "bool_get", "relation": "references", "confidence": "EXTRACTED", "confidence_score": 1.0, "source_file": "lib/core/storage/isar/product_cache.dart", "source_location": null, "weight": 1.0, "context": "variable_type"}, {"source": "users_abdullah_waslaq_app_lib_core_storage_isar_product_cache_dart", "target": "package_isar_isar_dart", "relation": "imports", "confidence": "EXTRACTED", "confidence_score": 1.0, "source_file": "lib/core/storage/isar/product_cache.dart", "source_location": null, "weight": 1.0}]}